diff_dot/__init__.py
diff_dot/cd.py
diff_dot/cmd.py
diff_dot/dependencies.py
diff_dot/diff_render.py
diff_dot/dot.py
diff_dot/dot_file.py
diff_dot/error.py
diff_dot/git_utils.py
diff_dot/graph_diff.py
diff_dot/graph_file.py
diff_dot/cli/__init__.py
diff_dot/cli/commands.py
diff_dot/cli/diff.py
diff_dot/cli/git_gradle_diff.py
diff_dot/cli/tests.py
diff_dot/gradle/__init__.py
diff_dot-2025.3.11.1.dist-info/METADATA
diff_dot-2025.3.11.1.dist-info/WHEEL
diff_dot-2025.3.11.1.dist-info/entry_points.txt
diff_dot-2025.3.11.1.dist-info/RECORD
