Metadata-Version: 2.4
Name: diff-dot
Version: 2025.3.11.1
Summary: Compare Directional Graphs
Requires-Python: >=3.12
Requires-Dist: click>=8.1.3
Requires-Dist: gitpython>=3.1.32
Requires-Dist: networkx>=3.1
Requires-Dist: pytest>=8.3.4
Requires-Dist: rich>=13.5.2
